image_object_slicer/COCOParser.py
image_object_slicer/CVATImagesParser.py
image_object_slicer/DatumaroParser.py
image_object_slicer/KITTIParser.py
image_object_slicer/LabelMeParser.py
image_object_slicer/MultipleFileAnnotationParser.py
image_object_slicer/OpenImagesParser.py
image_object_slicer/PascalVOCParser.py
image_object_slicer/SingleFileAnnotationParser.py
image_object_slicer/WIDERFaceParser.py
image_object_slicer/YOLOParser.py
image_object_slicer/__init__.py
image_object_slicer-1.12.3.data/scripts/image-object-slicer
image_object_slicer-1.12.3.dist-info/LICENSE
image_object_slicer-1.12.3.dist-info/METADATA
image_object_slicer-1.12.3.dist-info/WHEEL
image_object_slicer-1.12.3.dist-info/top_level.txt
image_object_slicer-1.12.3.dist-info/RECORD
