Metadata-Version: 2.1
Name: image-object-slicer
Version: 1.12.3
Summary: Slice images using annotation files.
Home-page: https://www.github.com/natanjunges/image-object-slicer
Author: Natan Junges
Author-email: natanajunges@gmail.com
License: GNU GPLv3+
License-File: LICENSE
Requires-Dist: pillow
Requires-Dist: tqdm
